fastshopifyapi/__init__.py
fastshopifyapi/__version__.py
fastshopifyapi/constants.py
fastshopifyapi/deferrer.py
fastshopifyapi/models.py
fastshopifyapi/options.py
fastshopifyapi/store.py
fastshopifyapi/types.py
fastshopifyapi/utils.py
fastshopifyapi/clients/__init__.py
fastshopifyapi/clients/async_client.py
fastshopifyapi/clients/client.py
fastshopifyapi/clients/common.py
fastshopifyapi-2.0.2.dist-info/LICENSE
fastshopifyapi-2.0.2.dist-info/METADATA
fastshopifyapi-2.0.2.dist-info/WHEEL
fastshopifyapi-2.0.2.dist-info/top_level.txt
fastshopifyapi-2.0.2.dist-info/RECORD
