Metadata-Version: 2.1
Name: fastshopifyapi
Version: 2.0.2
Summary: A read-to-use sync/async client for REST and GraphQL API calls to Shopify's API
Home-page: https://github.com/sokoslee/FastShopifyApi
Author: Sokos Lee
Author-email: Tyler King <tyler@osiset.com>, Sokos Lee <SokosLee@gmail.com>
License: MIT License
Project-URL: Homepage, https://github.com/sokoslee/FastShopifyApi
Project-URL: Bug Tracker, https://github.com/sokoslee/FastShopifyApi/issues
Platform: Any
Classifier: License :: OSI Approved :: MIT License
Classifier: Programming Language :: Python :: 3.8
Classifier: Programming Language :: Python :: 3.9
Classifier: Programming Language :: Python :: 3.10
Classifier: Programming Language :: Python :: 3.11
Classifier: Programming Language :: Python :: 3.12
Classifier: Programming Language :: Python :: 3 :: Only
Requires-Python: >=3.8
License-File: LICENSE
Requires-Dist: httpx (>=0.24.1)
